[
  {
    "title": "Taller sobre diseño web nivel básico, para programadores (Claudia Lopez Iglesias)",
    "start": "2017-01-30T8:15:00",
    "end": "2017-01-30T11:15:00",
    "backgroundColor": "#F88015",
    "url": "#m1"
  },
  {
    "title": "Android: Iniciación a las ROMs cocinadas",
    "start": "2017-01-30T8:15:00",
    "end": "2017-01-30T9:15:00",
    "backgroundColor": "#CE1212",
    "url": "#m2"
  },
  {
    "title": "TeamViewer (control de acceso remoto)",
    "start": "2017-01-30T9:15:00",
    "end": "2017-01-30T10:15:00",
    "backgroundColor": "#CE1212",
    "url": "#m3"
  },
  {
    "title": "Taller de Scratch",
    "start": "2017-01-30T10:15:00",
    "end": "2017-01-30T12:40:00",
    "backgroundColor": "#CE1212",
    "url": "#m4"
  },
  {
    "title": "Introducción a MaterializeCSS",
    "start": "2017-01-30T12:40:00",
    "end": "2017-01-30T13:40:00",
    "backgroundColor": "#7399F9",
    "url": "#m5"
  },
  {
    "title": "Taller de Scratch (Sesión 1 - 2ºBACH B-C)",
    "start": "2017-01-30T12:40:00",
    "end": "2017-01-30T13:40:00",
    "backgroundColor": "#CE1212",
    "url": "#m6"
  },
  {
    "title": "Proyectos con Raspberry Pi",
    "start": "2017-01-30T13:40:00",
    "end": "2017-01-30T14:40:00",
    "backgroundColor": "#7399F9",
    "url": "#m7"
  },
  {
    "title": "Metodologías de gestión ágil de proyectos",
    "start": "2017-01-31T8:15:00",
    "end": "2017-01-31T9:15:00",
    "backgroundColor": "#9D3283",
    "url": "#m8"
  },
  {
    "title": "Conceptos básicos de EmberJS",
    "start": "2017-01-31T9:15:00",
    "end": "2017-01-31T10:15:00",
    "backgroundColor": "#F88015",
    "url": "#m9"
  },
  {
    "title": "Monitorización de logs con el stack ELK",
    "start": "2017-01-31T9:15:00",
    "end": "2017-01-31T10:15:00",
    "backgroundColor": "#9D3283",
    "url": "#m10"
  },
  {
    "title": "Desarrollo de Apps móviles y proyectos Web",
    "start": "2017-01-31T10:15:00",
    "end": "2017-01-31T11:15:00",
    "backgroundColor": "#9D3283",
    "url": "#m11"
  },
  {
    "title": "Taller de introducción a WebGL con three.js",
    "start": "2017-01-31T11:15:00",
    "end": "2017-01-31T14:40:00",
    "backgroundColor": "#F88015",
    "url": "#m12"
  },
  {
    "title": "Ingeniería Social y phishing",
    "start": "2017-02-01T8:15:00",
    "end": "2017-02-01T9:15:00",
    "backgroundColor": "#F88015",
    "url": "#m13"
  },
  {
    "title": "Taller de Scratch (Sesión 1 - 2ºBACH A-C)",
    "start": "2017-02-01T9:15:00",
    "end": "2017-02-01T10:15:00",
    "backgroundColor": "#CE1212",
    "url": "#m14"
  },
  {
    "title": "IKNX. Programación en el mundo real",
    "start": "2017-02-01T9:30:00",
    "end": "2017-02-01T10:15:00",
    "backgroundColor": "#9D3283",
    "url": "#m15"
  },
  {
    "title": "IKNX. Proyectos KNX.",
    "start": "2017-02-01T10:15:00",
    "end": "2017-02-01T11:15:00",
    "backgroundColor": "#9D3283",
    "url": "#m16"
  },
  {
    "title": "IKNX. Demostración programación ETS",
    "start": "2017-02-01T11:40:00",
    "end": "2017-02-01T12:15:00",
    "backgroundColor": "#9D3283",
    "url": "#m17"
  },
  {
    "title": "Demostración cámaras CCTV de Fermax",
    "start": "2017-02-01T12:15:00",
    "end": "2017-02-01T14:00:00",
    "backgroundColor": "#9D3283",
    "url": "#m18"
  },
  {
    "title": "¿Por qué formarse en seguridad Informática?",
    "start": "2017-02-02T8:15:00",
    "end": "2017-02-02T9:30:00",
    "backgroundColor": "#9D3283",
    "url": "#m19"
  },
  {
    "title": "Fugas de Información en la Red",
    "start": "2017-02-02T9:30:00",
    "end": "2017-02-02T10:30:00",
    "backgroundColor": "#9D3283",
    "url": "#m20"
  },
  {
    "title": "MSOC-Guardianes del Ciberespacio",
    "start": "2017-02-02T11:00:00",
    "end": "2017-02-02T12:30:00",
    "backgroundColor": "#9D3283",
    "url": "#m21"
  },
  {
    "title": "Introducción a la Seguridad en el Internet de las Cosas",
    "start": "2017-02-02T12:30:00",
    "end": "2017-02-02T13:30:00",
    "backgroundColor": "#9D3283",
    "url": "#m22"
  },
  {
    "title": "Mesa Redonda",
    "start": "2017-02-02T13:30:00",
    "end": "2017-02-02T14:40:00",
    "backgroundColor": "#9D3283",
    "url": "#m23"
  },
  {
    "title": "Mobile MKT",
    "start": "2017-02-03T8:15:00",
    "end": "2017-02-03T9:15:00",
    "backgroundColor": "#9D3283",
    "url": "#m24"
  },
  {
    "title": "Taller de modificación de plantillas en WordPress",
    "start": "2017-02-03T9:15:00",
    "end": "2017-02-03T11:15:00",
    "backgroundColor": "#8FADFA",
    "url": "#m25"
  },
  {
    "title": "Introducción al SEO",
    "start": "2017-02-03T11:40:00",
    "end": "2017-02-03T12:40:00",
    "backgroundColor": "#9D3283",
    "url": "#m26"
  },
  {
    "title": "Taller de Scratch (Sesión 2 - 2ºBACH)",
    "start": "2017-02-03T11:40:00",
    "end": "2017-02-03T12:40:00",
    "backgroundColor": "#CE1212",
    "url": "#m27"
  },
  {
    "title": "Sweet Honey Alabama",
    "start": "2017-02-03T12:40:00",
    "end": "2017-02-03T13:40:00",
    "backgroundColor": "#7399F9",
    "url": "#m28"
  },
   {
    "title": "DAWMANA 2017",
    "start": "2017-01-30",
    "end": "2017-02-04",
    "backgroundColor": "#7399F9",
    "url": ""
  }

]
